akr_ext_animepahe/__init__.py
akr_ext_animepahe/animepahe.py
akr_ext_animepahe-0.0.0.dist-info/LICENSE
akr_ext_animepahe-0.0.0.dist-info/METADATA
akr_ext_animepahe-0.0.0.dist-info/WHEEL
akr_ext_animepahe-0.0.0.dist-info/top_level.txt
akr_ext_animepahe-0.0.0.dist-info/RECORD
