Metadata-Version: 2.1
Name: akr_ext_animepahe
Version: 0.0.0
Summary: An anime bot to download your favourite animes
Home-page: https://github.com/GhoulKingR/AKR_extensions_sdk
Author: GhoulKingR
Author-email: oduahchigozie46@gmail.com
License: MIT
License-File: LICENSE
Requires-Dist: setuptools ==68.1.2
Requires-Dist: akr-extensions-sdk
